{
    "1": "1",
    "AmazonProfile": "Профіль на Amazon",
    "Approval": "Схвалення",
    "Blank": "Пустий",
    "Code": "Код",
    "Delete": "Видалити",
    "Filter": "Фільтр",
    "Format": "Формат",
    "Inactive": "Неактивний",
    "ListColon": "Список:",
    "Name": "Ім&#39;я",
    "Order": "Замовлення",
    "Organization": "Організація",
    "Primary": "Первинний",
    "Readonly": "Тільки для читання",
    "Reset": "Скинути",
    "Save": "Зберегти",
    "SaveAndNew": "Зберегти та створити новий",
    "Sort": "Сортувати",
    "Submit": "Надіслати",
    "Temporary": "Тимчасовий",
    "TextSearch": "Пошук тексту",
    "Type": "Тип",
    "TypeID": "Тип №",
    "ViewEdit": "Переглянути / Редагувати:",
    "ViewEditColon": "Переглянути / Редагувати:"
}