{
    "1": "1",
    "ActionReq": "Action requise",
    "ActionReqDot": "Action requise",
    "ActionRequired": "Action requise",
    "Blank": "Vide",
    "Comment": "Commentaire",
    "CommentID": "Commentaire #",
    "CommentType": "Type de commentaire",
    "Datetime": "Date et heure",
    "Delete": "Supprimer",
    "ExternalIntegrationTypeCode": "Code de type d&#39;intégration externe",
    "Files": "Fichier(s)",
    "Filter": "Filtre",
    "FollowUpDatetime": "Date et heure de suivi",
    "Format": "Format",
    "Important": "Important",
    "Inactive": "Inactif",
    "ListColon": "Liste:",
    "Name": "Nom",
    "New": "Nouveau",
    "Number": "#",
    "Order": "Commande",
    "Organization": "Organisation",
    "PleaseChoose": "Veuillez choisir",
    "Public": "Publique",
    "Reset": "Réinitialiser",
    "Save": "Sauvegarder",
    "SaveAndNew": "Enregistrer et nouveau",
    "Sort": "Trier",
    "Submit": "Soumettre",
    "Template": "Modèle",
    "TemplateID": "Modèle #",
    "TextSearch": "Recherche de texte",
    "Type": "Taper",
    "User": "Utilisateur",
    "ViewEdit": "Afficher / Modifier :",
    "ViewEditColon": "Afficher / Modifier :"
}